{
  "online": [
    {
      "date": 1553010360221,
      "count": "57757"
    },
    {
      "date": 1553010425181,
      "count": "57766"
    },
    {
      "date": 1553010480172,
      "count": "57766"
    }
  ],
  "members": [
    {
      "date": 1553010360221,
      "count": "50635"
    },
    {
      "date": 1553010425182,
      "count": "50660"
    },
    {
      "date": 1553010480172,
      "count": "50660"
    }
  ],
  "visitors": [
    {
      "date": 1553010360221,
      "count": "7122"
    },
    {
      "date": 1553010425182,
      "count": "7106"
    },
    {
      "date": 1553010480172,
      "count": "7106"
    }
  ]
}